flake8_spaces_around_constants.py
flake8_spaces_around_constants-1.0.dist-info/METADATA
flake8_spaces_around_constants-1.0.dist-info/WHEEL
flake8_spaces_around_constants-1.0.dist-info/entry_points.txt
flake8_spaces_around_constants-1.0.dist-info/top_level.txt
flake8_spaces_around_constants-1.0.dist-info/RECORD
