Metadata-Version: 2.1
Name: flake8-spaces-around-constants
Version: 1.0
Summary: Check whether your constant values have leading or trailing spaces
Home-page: https://github.com/vikingco/flake8-spaces-around-constants
Author: Unleashed NV
Author-email: development@unleashed.be
License: MIT
Keywords: flake8 constants leading trailing space
Platform: UNKNOWN
Classifier: Development Status :: 3 - Alpha
Classifier: Environment :: Console
Classifier: Intended Audience :: Developers
Classifier: License :: OSI Approved :: MIT License
Classifier: Operating System :: OS Independent
Classifier: Programming Language :: Python
Classifier: Programming Language :: Python :: 2
Classifier: Programming Language :: Python :: 3
Classifier: Topic :: Software Development :: Libraries :: Python Modules
Classifier: Topic :: Software Development :: Quality Assurance
Requires-Dist: flake8
